{"items":[{"id":662,"image":"2","text":"Hot Wheels 2005 Ferrari F430 (1:72)"},{"id":1488,"image":"6","text":"Schuco B66962234 2005 Maybach Exelero Concept (1:43)"},{"id":1047,"image":"3","text":"CM's Corp. SSC 2005 Subaru Impreza GD WRC2005 (1:64)"},{"id":1053,"image":"4","text":"CM's Corp. SSC 2005 Subaru Impreza GD WRC2005 (1:64)"},{"id":299,"image":"3","text":"IXO RAM199 2005 Subaru Impreza GD WRC2005 Acropolis Rally K. Sohlberg (1:43)"},{"id":429,"image":"1","text":"Norev 800151 2005 Mitsubishi Pajero Evolution Dakar Rally 1st S. Peterhansel (1:43)"},{"id":670,"image":"9","text":"Solido 9066 2005 Mitsubishi Pajero Evolution Dakar Rally 1st S. Peterhansel (1:18)"},{"id":1515,"image":"5","text":"Norev 518810 2005 Hino Ranger Dakar Rally 2nd Y. Sugawara (1:43)"},{"id":1238,"image":"6","text":"Norev 840250 2005 Volkswagen Race Touareg 2 Dakar Rally 3rd J. Kleinschmidt (1:43)"},{"id":744,"image":"4","text":"Diamondlabel 62866 2005 DAF FAV CF75.530 Dakar Rally 4th J. De Rooy (1:50)"},{"id":982,"image":"7","text":"Diamondlabel 62865 2005 DAF FAV CF75.530 Dakar Rally 5th G. De Rooy (1:50)"},{"id":380,"image":"14","text":"Minipartes MNP210 2005 Nissan Navara Dakar Rally 7th C. Sousa (1:43)"},{"id":716,"image":"5","text":"Spark S0497 2005 BMW X5 Dakar Rally 9th J. L. Monterde (1:43)"},{"id":416,"image":"37","text":"Minichamps 436055317 2005 Volkswagen Race Touareg Dakar Rally 12th R. Gordon (1:43)"},{"id":437,"image":"5","text":"Spark S0496 2005 BMW X5 Dakar Rally DNF N. Al-Attiyah (1:43)"},{"id":732,"image":"14","text":"TOYS 54.1347 2005 Ginaf X2222 SP Dakar Rally DNF W. Van Ginkel (1:43)"},{"id":1501,"image":"12","text":"Ebbro 43771 2005 Toyota Supra (JZA80) JGTC Series 1st Y. Tachikawa (1:43)"},{"id":129,"image":"1","text":"Action 109402 2005 Chevrolet Monte Carlo NASCAR Series 41st D. Hamlin (1:24)"},{"id":887,"image":"4","text":"CM's Corp. CMM.2 #7 2005 &#352;koda Fabia WRC Rally Australia DNF C. McRae (1:64)"},{"id":2114,"image":"5","text":"AUTOart 80517 2005 Toyota Supra Super GT Series 1st T. Takagi (1:18)"},{"id":1217,"image":"22","text":"Ebbro 43692 2005 Honda NSX Super GT Series 9th A. Lotterer (1:43)"},{"id":1216,"image":"20","text":"Ebbro 43690 2005 Honda NSX Super GT Series 10th T. Kogure (1:43)"},{"id":1765,"image":"12","text":"HPI 931 2005 Subaru Impreza STi Super Taikyu Series 1st Y. Toshihiro (1:43)"},{"id":1155,"image":"10","text":"IXO RAM167 2005 Citro&#235;n Xsara WRC Rallye Monte Carlo 1st S. Loeb (1:43)"},{"id":895,"image":"1","text":"CM's Corp. SS.16 Secret 2005 Ford Focus RS WRC 05 Rallye Monte Carlo 2nd T. Gardemeister (1:64)"},{"id":798,"image":"4","text":"CM's Corp. SS.7 #6 2005 Mitsubishi Lancer WRC 05 Rallye Monte Carlo 3rd G. Panizzi (1:64)"},{"id":318,"image":"5","text":"AUTOart 60555 2005 Peugeot 307 WRC Rallye Monte Carlo 4th M. Martin (1:43)"},{"id":735,"image":"1","text":"AUTOart 80555 2005 Peugeot 307 WRC Evo 2 Rallye Monte Carlo 4th M. M&#228;rtin (1:18)"},{"id":243,"image":"1","text":"IXO RAM170 2005 Peugeot 307 Rallye Monte Carlo 5th M. Gr&#246;nholm (1:43)"},{"id":336,"image":"9","text":"Norev 155253 2005 Citro&#235;n C2 Super 1600 Rallye Monte Carlo 11th K. Meeke (1:43)"},{"id":335,"image":"7","text":"Spark S0626 2005 Suzuki Ignis S1600 Rallye Monte Carlo 20th M. Prokop (1:43)"},{"id":1003,"image":"4","text":"IXO 05-SWEDEN-43 2005 Subaru Impreza GD WRC2004 Swedish Rally 1st P. Solberg (1:43)"},{"id":244,"image":"1","text":"IXO RAM178 2005 Subaru Impreza GD WRC2004 Swedish Rally 1st P. Solberg (1:43)"},{"id":457,"image":"1","text":"IXO RAM183 2005 Peugeot 307 Swedish Rally 2nd M. M&#228;rtin (1:43)"},{"id":245,"image":"1","text":"IXO RAM180 2005 Mitsubishi Lancer WRC 05 Swedish Rally 4th H. Rovanpera (1:43)"},{"id":246,"image":"5","text":"IXO RAM182 2005 Ford Focus RS WRC 05 Swedish Rally 5th H. Solberg (1:43)"},{"id":1180,"image":"7","text":"AUTOart 60592 2005 Subaru Impreza GD WRC2005 Rally M&#233;xico 1st P. Solberg (1:43)"},{"id":962,"image":"4","text":"CM's Corp. SC #12 2005 Subaru Impreza GD WRC2005 Rally M&#233;xico 1st P. Solberg (1:64)"},{"id":775,"image":"8","text":"CM's Corp. SS.4 #5 2005 Subaru Impreza GD WRC2005 Rally M&#233;xico 1st P. Solberg (1:64)"},{"id":247,"image":"3","text":"IXO RAM184 2005 Subaru Impreza GD WRC2005 Rally M&#233;xico 1st P. Solberg (1:43)"},{"id":64,"image":"1","text":"DeAgostini Rally Car Collection #59 2005 Ford Focus RS WRC 04 Rally M&#233;xico DNF D. Sol&#224; (1:43)"},{"id":254,"image":"1","text":"IXO RAM223 2005 Subaru Impreza GD WRC2005 Rallye de Portugal C. Sainz (1:43)"},{"id":461,"image":"1","text":"IXO RAM187 2005 Subaru Impreza GD WRC2005 Rally New Zealand 7th C. Atkinson (1:43)"},{"id":249,"image":"1","text":"IXO RAM189 2005 Ford Focus RS WRC 04 Rally New Zealand 11th A. Warmbold (1:43)"},{"id":356,"image":"7","text":"IXO RAM190 2005 Mitsubishi Lancer WRC 05 Rally New Zealand 13th X. Pons (1:43)"},{"id":1240,"image":"6","text":"IXO RAM191 2005 Citro&#235;n Xsara WRC Rally d'Italia Sardegna 1st S. Loeb (1:43)"},{"id":439,"image":"1","text":"IXO RAM192 2005 Citro&#235;n Xsara WRC Rally d'Italia Sardegna 8th J. Pyk&#228;listo (1:43)"},{"id":298,"image":"3","text":"IXO RAM194 2005 Ford Focus RS WRC 05 Rally d'Italia Sardegna 10th M. Higgins (1:43)"},{"id":458,"image":"1","text":"IXO RAM197 2005 Citro&#235;n Xsara WRC Rally of Turkey 4th C. Sainz (1:43)"},{"id":250,"image":"1","text":"IXO RAM201 2005 Peugeot 307 Rally Argentina 2nd M. M&#228;rtin (1:43)"},{"id":859,"image":"2","text":"CM's Corp. SS.8.5 #8 2005 Peugeot 307 WRC Rally Finland 1st M. Gr&#246;nholm (1:64)"},{"id":1179,"image":"5","text":"IXO RAM202 2005 Peugeot 307 WRC Evo 2 Rally Finland 1st M. Gr&#246;nholm (1:43)"},{"id":441,"image":"1","text":"IXO RAM204 2005 Ford Focus RS WRC 05 Rally Finland 5th M. Hirvonen (1:43)"},{"id":1057,"image":"1","text":"CM's Corp. JAPANBOX.15 2005 Suzuki Swift S1600 Rally Finland 18th G. Wilks (1:64)"},{"id":319,"image":"4","text":"AUTOart 60556 2005 Peugeot 307 WRC Rallye Deutschland 3rd M. Gronholm (1:43)"},{"id":940,"image":"4","text":"CM's Corp. JAPANBOX.5 2005 Peugeot 307 WRC Rally Japan 1st M. Gr&#246;nholm (1:64)"},{"id":1313,"image":"1","text":"CM's Corp. JAPAN.15 2005 Peugeot 307 WRC Evo 2 Rally Japan 1st M. Gr&#246;nholm (1:64)"},{"id":1310,"image":"1","text":"CM's Corp. JAPAN.11 2005 Citro&#235;n Xsara WRC Rally Japan 2nd S. Loeb (1:64)"},{"id":936,"image":"4","text":"CM's Corp. JAPANBOX.1 2005 Citro&#235;n Xsara WRC Rally Japan 2nd S. Loeb (1:64)"},{"id":929,"image":"4","text":"CM's Corp. JAPANBOX.4 2005 Subaru Impreza GD WRC2005 Rally Japan 3rd C. Atkinson (1:64)"},{"id":329,"image":"8","text":"HPI 933 2005 Subaru Impreza GD WRC2005 Rally Japan 3rd C. Atkinson (1:43)"},{"id":937,"image":"4","text":"CM's Corp. JAPANBOX.2 2005 Citro&#235;n Xsara WRC Rally Japan 4th F. Duval (1:64)"},{"id":930,"image":"4","text":"CM's Corp. JAPANBOX.7 2005 Mitsubishi Lancer WRC Rally Japan 5th H. Rovanper&#228; (1:64)"},{"id":1308,"image":"1","text":"CM's Corp. JAPAN.9 2005 Ford Focus RS WRC 05 Rally Japan 6th T. Gardemeister (1:64)"},{"id":1309,"image":"1","text":"CM's Corp. JAPAN.10 2005 Ford Focus RS WRC 05 Rally Japan 7th R. Kresta (1:64)"},{"id":933,"image":"5","text":"CM's Corp. JAPANBOX.6 2005 Peugeot 307 WRC Rally Japan 8th D. Carlsson (1:64)"},{"id":934,"image":"4","text":"CM's Corp. JAPANBOX.9 2005 &#352;koda Fabia WRC Rally Japan 10th A. Schwarz (1:64)"},{"id":931,"image":"4","text":"CM's Corp. JAPANBOX.8 2005 Mitsubishi Lancer WRC Rally Japan 11th G. Panizzi (1:64)"},{"id":847,"image":"1","text":"CM's Corp. ARAI #6 2005 Subaru Impreza GD WRC2005 Rally Japan 12th T. Arai (1:64)"},{"id":1055,"image":"3","text":"CM's Corp. JAPANBOX.11 2005 Suzuki Swift S1600 Rally Japan 17th G. Wilks (1:64)"},{"id":935,"image":"4","text":"CM's Corp. JAPANBOX.10 2005 &#352;koda Fabia WRC Rally Japan DNF M. Hirvonen (1:64)"},{"id":928,"image":"4","text":"CM's Corp. JAPANBOX.3 2005 Subaru Impreza GD WRC2005 Rally Japan DNF P. Solberg (1:64)"},{"id":1756,"image":"11","text":"HPI 932 2005 Subaru Impreza GD WRC2005 Rally Japan DNF P. Solberg (1:43)"}]}