{"items":[{"id":1912,"image":"2","text":"Luppa Colleción 2014 Mini All4 Dakar Rally 1st N. Roma (1:43)"},{"id":1606,"image":"5","text":"Eaglemoss Collections Passione Rally #115 2014 Hyundai i20 (1st Gen) Rallye Deutschland 1st T. Neuville (1:43)"},{"id":1750,"image":"5","text":"IXO RAM597 2014 Volkswagen Polo R Rallye de France 1st J. M. Latvala (1:43)"},{"id":1535,"image":"13","text":"IXO RAM601 2014 Ford Fiesta RS Rally Catalunya &#8211; Costa Daurada 12th K. Block (1:43)"},{"id":1896,"image":"3","text":"IXO 18RMC017 2014 Ford Fiesta RS Rally Catalunya &#8211; Costa Daurada 12th K. Block (1:18)"}]}