{"items":[{"id":1749,"image":"12","text":"IXO RAC119 1986 Peugeot 205 T16 E2 Acropolis Rally 1st J. Kankkunen (1:43)"},{"id":93,"image":"1","text":"DeAgostini Rally Car Collection #46 1986 Porsche 959 Paris-Dakar Rally 1st R. Metge (1:43)"},{"id":1078,"image":"4","text":"Minichamps WAPC20SET01.3 1986 Porsche 959 Paris-Dakar Rally 1st R. Metge (1:43)"},{"id":907,"image":"1","text":"CM's Corp. MITSUBISHI.1 #1 1986 Mitsubishi Starion 4WD Hong Kong Beijing Rally 2nd (1:64)"},{"id":901,"image":"2","text":"CM's Corp. SS.17 #6 1986 Mitsubishi Starion 4WD Hong Kong Beijing Rally 2nd N. Lu (1:64)"},{"id":84,"image":"1","text":"DeAgostini Rally Car Collection #34 1986 Peugeot 205 T16 E2 1000 Lakes Rally 1st T. Salonen (1:43)"},{"id":900,"image":"2","text":"CM's Corp. SS.17 #5 1986 Mitsubishi Starion 4WD 1000 Lakes Rally DNF A. Laine (1:64)"},{"id":1279,"image":"5","text":"Bizarre BZ216 1986 Toyota Celica Twincam Turbo Safari Rally 1st B. Waldeg&#229;rd (1:43)"},{"id":1633,"image":"10","text":"HPI 8936 1986 Toyota Celica Twincam Turbo Safari Rally 1st B. Waldeg&#229;rd (1:43)"},{"id":1646,"image":"10","text":"HPI 8231 1986 Lancia 037 Evo Safari Rally 3rd M. Al&#233;n (1:43)"},{"id":1652,"image":"1","text":"HPI 8841 1986 Ford RS200 Acropolis Rally DNF K. Grundel (1:43)"},{"id":970,"image":"4","text":"CM's Corp. LC #5 1986 Lancia Delta S4 Rallye Monte Carlo 1st H. Toivonen (1:64)"},{"id":768,"image":"1","text":"CM's Corp. SS.3 #4 1986 Lancia Delta S4 Rallye Monte Carlo 1st H. Toivonen (1:64)"},{"id":781,"image":"4","text":"CM's Corp. SS.5 #3 1986 Lancia Delta S4 Rallye Monte Carlo 1st H. Toivonen (1:64)"},{"id":1731,"image":"18","text":"HPI 966 1986 Lancia Delta S4 Rallye Monte Carlo 1st H. Toivonen (1:43)"},{"id":447,"image":"8","text":"HPI 8036.2 1986 Lancia Delta S4 Rallye Monte Carlo 1st H. Toivonen (1:43)"},{"id":878,"image":"1","text":"CM's Corp. SS.15 #5 1986 Mazda 323 4WD Rallye Monte Carlo DNF I. Carlsson (1:64)"},{"id":916,"image":"2","text":"CM's Corp. SS.19 #1 1986 Citro&#235;n BX 4TC Rallye Monte Carlo DNF J. C. Andruet (1:64)"},{"id":46,"image":"1","text":"DeAgostini Rally Car Collection #43 1986 Citro&#235;n BX 4TC Rallye Monte Carlo DNF J. C. Andruet (1:43)"},{"id":219,"image":"1","text":"IXO RAC095 1986 Citro&#235;n BX 4TC Rallye Monte Carlo DNF J. C. Andruet (1:43)"},{"id":322,"image":"17","text":"IXO RAC075 1986 Peugeot 205 T16 E2 Rallye Monte Carlo DNF M. Mouton (1:43)"},{"id":323,"image":"19","text":"IXO RAC033 1986 MG Metro 6R4 Rallye Monte Carlo DNF T. Pond (1:43)"},{"id":889,"image":"1","text":"CM's Corp. SS.16 #1 1986 Ford RS200 Swedish Rally 3rd K. Grundel (1:64)"},{"id":65,"image":"1","text":"DeAgostini Rally Car Collection #15 1986 Ford RS200 Swedish Rally 3rd K. Grundel (1:43)"},{"id":1878,"image":"1","text":"HPI 8343 1986 Ford RS200 Swedish Rally 3rd K. Grundel (1:43)"},{"id":1692,"image":"8","text":"HPI 8036.1 1986 Lancia Delta S4 Tour de Corse DNF H. Toivonen (1:43)"},{"id":1152,"image":"5","text":"Universal Hobbies UH1708 1986 Renault 5 Turbo 2 Rallye de Portugal 1st J. Moutinho (1:43)"},{"id":301,"image":"7","text":"IXO RAC066 1986 Ford RS200 Ypres 24 Hours Rally 1st R. Droogmans (1:43)"},{"id":741,"image":"1","text":"Altaya 1986 Renault 5 Maxi Turbo Rally Principe de Asturias 2nd C. Sainz (1:43)"},{"id":1626,"image":"12","text":"HPI 967 1986 Lancia Delta S4 Rallye Sanremo 1st M. Al&#233;n (1:43)"},{"id":1732,"image":"9","text":"HPI 8052.1 1986 Lancia Delta S4 Rallye Sanremo 1st M. Al&#233;n (1:43)"},{"id":1696,"image":"1","text":"HPI 968 1986 Lancia Delta S4 Rallye Sanremo 2nd D. Cerrato (1:43)"},{"id":1736,"image":"8","text":"HPI 8052.2 1986 Lancia Delta S4 Rallye Sanremo 2nd D. Cerrato (1:43)"},{"id":1416,"image":"5","text":"HPI 8641 1986 Lancia Delta S4 Rallye Sanremo DNF F. Tabaton (1:43)"},{"id":1365,"image":"7","text":"HPI 8843 1986 Ford RS200 RAC Rally 5th K. Grundel (1:43)"},{"id":1372,"image":"7","text":"HPI 8637 1986 Lancia Delta S4 Olympus Rally 1st M. Al&#233;n (1:43)"}]}