{"images":["1","2","3","4","5","6","12","18","19","20","21","22"],"scale":"1:43","brand":"Rai's","catalogNo":"H7437103","manufacturer":"Nissan","model":"Skyline 2000GT-R (KPGC10)","year":1971,"event":"Fuji Masters 250km TC-B","eventCode":"Fuji Masters 250km","carNumber":3,"driver1":"M. Kurosawa","notes":"<A HREF=\"https://motorsports.jaf.or.jp/results/search/1971/race/1971-9999-111\" TARGET=\"_blank\">https://motorsports.jaf.or.jp/results/search/1971/race/1971-9999-111</A><BR/><BR/><A HREF=\"http://www.hiko7plus.co.jp/item/H7437103/\" TARGET=\"_blank\">http://www.hiko7plus.co.jp/item/H7437103/</A><BR/><BR/><A HREF=\"http://www14.plala.or.jp/reinik-z/racing/kpgc10/kpgc10.html\" TARGET=\"_blank\">http://www14.plala.or.jp/reinik-z/racing/kpgc10/kpgc10.html</A><BR/><BR/><A HREF=\"http://www.jaf.or.jp/CGI/msports/results/n-race/detail-result.cgi?race_id=1712\" TARGET=\"_blank\">http://www.jaf.or.jp/CGI/msports/results/n-race/detail-result.cgi?race_id=1712</A><BR/><BR/><A HREF=\"http://www.nissan-global.com/EN/HERITAGE/short_story/en_p36-01.html\" TARGET=\"_blank\">http://www.nissan-global.com/EN/HERITAGE/short_story/en_p36-01.html</A><BR/><BR/>win #49<BR/><BR/><A HREF=\"http://vital.sakura.ne.jp/NISSAN%20SKYLINE%20KGC10%20HP/kaihatu.html\" TARGET=\"_blank\">http://vital.sakura.ne.jp/NISSAN%20SKYLINE%20KGC10%20HP/kaihatu.html</A><BR/><BR/><A HREF=\"https://picasaweb.google.com/109233223652492168348/Images645?authuser=0&authkey=Gv1sRgCMPAlt60stX6xQE&feat=directlink\" TARGET=\"_blank\">https://picasaweb.google.com/109233223652492168348/Images645?authuser=0&amp;authkey=Gv1sRgCMPAlt60stX6xQE&amp;feat=directlink</A><BR/><BR/><A HREF=\"https://picasaweb.google.com/109233223652492168348/Images647?authuser=0&authkey=Gv1sRgCOCUoea8irW7iwE&feat=directlink\" TARGET=\"_blank\">https://picasaweb.google.com/109233223652492168348/Images647?authuser=0&amp;authkey=Gv1sRgCOCUoea8irW7iwE&amp;feat=directlink</A><BR/><BR/><A HREF=\"http://www.scale143.com/viewtopic.php?f=31&t=8649&p=292361#p292361\" TARGET=\"_blank\">http://www.scale143.com/viewtopic.php?f=31&amp;t=8649&amp;p=292361#p292361</A><BR/><BR/><BR/><b>Rai&apos;s H7437103 Nissan Skyline 2000GT-R (KPGC10) 1971 Fuji Masters 250km Winner M. Kurosawa</b><BR/><BR/>Purchased: 2015<BR/>Manufacturer page: http://www.hiko7plus.co.jp/item/H7437103/<BR/><BR/>Again, see <A HREF=\"http://www.scale143.com/viewtopic.php?f=31&amp;t=8649&amp;p=291725#p291725\">here</A> for details on the race. Motoharu Kurosawa qualified in 2nd place but took the win.<BR/><BR/><BR/><BR/>   <BR/><BR/><BR/>Sources:<BR/><A HREF=\"http://vital.sakura.ne.jp/NISSAN%20SKYLINE%20KGC10%20HP/kaihatu.html\">SPIRIT OF SKYLINE</A><BR/>"}