{"images":["1","2","3","4","5","6","7","8","9","10"],"scale":"1:43","brand":"HPI","catalogNo":"8077","manufacturer":"Nissan","model":"BNR32 Skyline GT-R","year":1993,"event":"JTC/JTCC Series","eventCode":"JTC/JTCC Series","carNumber":11,"driver1":"T. Kristensen","driver2":"H. Yokoshima","competitionClass":"JTC-1","notes":"<A HREF=\"http://www.hpimodelcar.com/line_up/index_8077.php\" TARGET=\"_blank\">http://www.hpimodelcar.com/line_up/index_8077.php</A><BR/><BR/><A HREF=\"https://en.wikipedia.org/wiki/1993_Japanese_Touring_Car_Championship_season\" TARGET=\"_blank\">https://en.wikipedia.org/wiki/1993_Japanese_Touring_Car_Championship_season</A><BR/><BR/><A HREF=\"http://touringcarracing.net/Pages/1993%20AJTCC.html\" TARGET=\"_blank\">http://touringcarracing.net/Pages/1993%20AJTCC.html</A><BR/><BR/><A HREF=\"https://goo.gl/photos/FYhJUAuBdEKvKck27\" TARGET=\"_blank\">https://goo.gl/photos/FYhJUAuBdEKvKck27</A><BR/><BR/><A HREF=\"http://www.scale143.com/viewtopic.php?f=31&t=8649&p=317228#p317228\" TARGET=\"_blank\">http://www.scale143.com/viewtopic.php?f=31&amp;t=8649&amp;p=317228#p317228</A><BR/><BR/><BR/><b>HPI 8077 Nissan Skyline GT-R 1993 JTC Series 6th/5th Place H. Yokoshima/T. Kristensen</b><BR/><BR/>Tom Kristensen was knighted by the Queen of Denmark and holds the record for the most wins at the 24 Hours of Le Mans (9). While not nearly as exciting, he also drove in the JTC series in 1992 &amp; 1993 earning 2 wins.<BR/><BR/>Hisashi Yokoshima and Tom Kristensen dove this BP Oil Skyline for the Object T in the final season of the Group A-based JTC championship. Their best result was a win in round 9, the Fuji Inter-Tec 500 at Fuij Speedway. Yokoshima &amp; Kristensen finished the season in 6th &amp; 5th places respectively.<BR/><BR/><BR/><BR/> <BR/><BR/> <BR/><BR/>Sources:<BR/><A HREF=\"https://en.wikipedia.org/wiki/1993_Japanese_Touring_Car_Championship\">1993 Japanese Touring Car Championship - Wikipedia</A><BR/><A HREF=\"https://en.wikipedia.org/wiki/Tom_Kristensen_(racing_driver)\">Tom Kristensen (racing driver) - Wikipedia</A><BR/><A HREF=\"http://touringcarracing.net/Pages/1993%20AJTCC.html\">All-Japan Touring Car Championship - 1993</A><BR/>"}