{"images":["1","2","3","4","5","6","7","8"],"scale":"1:43","brand":"Spark","catalogNo":"SG014","manufacturer":"BMW","model":"M1 Turbo","year":1981,"event":"Norisring","eventCode":"DRM","carNumber":51,"driver1":"H. Stuck","competitionClass":"Group 5","notes":"<A HREF=\"https://www.american-excellence.com/v2/index.php?p=details&i=176047\" TARGET=\"_blank\">https://www.american-excellence.com/v2/index.php?p=details&amp;i=176047</A><BR/><BR/><A HREF=\"http://www.racingsportscars.com/photo/Norisring-1981-06-28.html\" TARGET=\"_blank\">http://www.racingsportscars.com/photo/Norisring-1981-06-28.html</A><BR/><BR/><A HREF=\"https://picasaweb.google.com/109233223652492168348/Images501?authuser=0&authkey=Gv1sRgCLz60PHG2JvvEw&feat=directlink\" TARGET=\"_blank\">https://picasaweb.google.com/109233223652492168348/Images501?authuser=0&amp;authkey=Gv1sRgCLz60PHG2JvvEw&amp;feat=directlink</A><BR/>"}