{"images":["1","2","3","4"],"scale":"1:43","brand":"Rêve Collection","catalogNo":"R70236","manufacturer":"Toyota","model":"Starlet","year":1978,"event":"Fuji Minor Touring Series","eventCode":"Fuji Minor Touring","carNumber":7,"driver1":"K. Hoshino","notes":"<A HREF=\"https://www.1999.co.jp/eng/10172301\" TARGET=\"_blank\">https://www.1999.co.jp/eng/10172301</A><BR/><BR/><A HREF=\"https://www.dailysportscar.com/2022/11/26/kaoru-hoshino-1947-2022.html\" TARGET=\"_blank\">https://www.dailysportscar.com/2022/11/26/kaoru-hoshino-1947-2022.html</A><BR/><BR/><A HREF=\"https://motor-fan.jp/weboption/article/94907/\" TARGET=\"_blank\">https://motor-fan.jp/weboption/article/94907/</A><BR/><BR/>Kaoru Hoshino<BR/><BR/>Fuji Victory 200km Race Minor Touring: <A HREF=\"https://motorsports.jaf.or.jp/results/search/1978/race/1978-9999-59\" TARGET=\"_blank\">https://motorsports.jaf.or.jp/results/search/1978/race/1978-9999-59</A><BR/><BR/>Fuji Masters 250 km Race Minor Touring: <A HREF=\"https://motorsports.jaf.or.jp/results/search/1978/race/1978-9999-49\" TARGET=\"_blank\">https://motorsports.jaf.or.jp/results/search/1978/race/1978-9999-49</A><BR/><BR/>Fuji Inter 200 Mile Race Minor Touring: <A HREF=\"https://motorsports.jaf.or.jp/results/search/1978/race/1978-9999-39\" TARGET=\"_blank\">https://motorsports.jaf.or.jp/results/search/1978/race/1978-9999-39</A><BR/><BR/>Fuji Grand 250kg Race Minor Touring: <A HREF=\"https://motorsports.jaf.or.jp/results/search/1978/race/1978-9999-30\" TARGET=\"_blank\">https://motorsports.jaf.or.jp/results/search/1978/race/1978-9999-30</A><BR/><BR/>Fuji 300 km Speed Race Minor Touring: <A HREF=\"https://motorsports.jaf.or.jp/results/search/1978/race/1978-9999-5\" TARGET=\"_blank\">https://motorsports.jaf.or.jp/results/search/1978/race/1978-9999-5</A><BR/>"}