{"items":[{"id":33,"image":"1","text":"Vitesse V98017 1997 Toyota Corolla (AE111) Rally Finland 8th D. Auriol (1:43)"},{"id":791,"image":"5","text":"CM's Corp. SS.6 #6 1998 Toyota Corolla (AE111) Rallye Catalunya - Costa Brava 7th C. Sainz (1:64)"},{"id":719,"image":"1","text":"AUTOart 80022 1998 Toyota Corolla (AE111) Rally Finland 2nd C. Sainz (1:18)"},{"id":36,"image":"2","text":"Skid SKM99002 1998 Toyota Corolla (AE111) Rally Malaysia 1st Y. Fujimoto (1:43)"},{"id":827,"image":"1","text":"CM's Corp. SS.12 Secret 1998 Toyota Corolla (AE111) Rally of Great Britain DNF C. Sainz (1:64)"},{"id":109,"image":"1","text":"DeAgostini Rally Car Collection #40 1999 Toyota Corolla (AE111) Rally Australia 2nd C. Sainz (1:43)"},{"id":1008,"image":"5","text":"Skid SKW99011 1999 Toyota Corolla (AE111) Rally China 1st D. Auriol (1:43)"},{"id":632,"text":"Skid SKM99042 1999 Toyota Corolla (AE111) Rally El Corte Ingl&#233;s (1:43)"},{"id":361,"image":"3","text":"AUTOart 69981 1999 Toyota Corolla (AE111) Safari Rally D. Auriol (1:43)"},{"id":681,"image":"22","text":"AUTOart 89982 1999 Toyota Corolla (AE111) Safari Rally 3rd C. Sainz (1:18)"},{"id":1268,"image":"6","text":"AUTOart 69982 1999 Toyota Corolla (AE111) Safari Rally 4th C. Sainz (1:43)"},{"id":450,"image":"1","text":"Skid SKM042 1999 Toyota Corolla (AE111) Rallye El Corte Ingl&#233;s DNF F. Delecour (1:43)"},{"id":338,"image":"9","text":"IXO RAC147 2000 Toyota Corolla (AE111) Rally Finland 10th M. M&#228;rtin (1:43)"},{"id":346,"image":"11","text":"IXO RAC145 2000 Toyota Corolla (AE111) Rally Finland DNF J. Tuohino (1:43)"},{"id":677,"image":"6","text":"IXO RAC062 2000 Toyota Corolla (AE111) Tour de Corse 9th S. Loeb (1:43)"},{"id":110,"image":"1","text":"DeAgostini Rally Car Collection #56 2004 Toyota Corolla (AE111) Monza Rally Show 3rd V. Rossi (1:43)"}]}