{"images":["2","3","4","5","6","7","8"],"scale":"1:43","brand":"HPI","catalogNo":"8224","manufacturer":"Lancia","model":"Delta Evo","year":1993,"event":"1000 Lakes Rally","eventCode":"Rally Finland","carNumber":13,"driver1":"T. Mäkinen","driver2":"S. Harjanne","competitionClass":"Group A","notes":"<A HREF=\"http://www.ewrc-results.com/final.php?e=536&t=1000-Lakes-Rally-1993\" TARGET=\"_blank\">http://www.ewrc-results.com/final.php?e=536&amp;t=1000-Lakes-Rally-1993</A><BR/><BR/><A HREF=\"http://hpimc-usa.jugem.jp/?eid=92\" TARGET=\"_blank\">http://hpimc-usa.jugem.jp/?eid=92</A><BR/><BR/><A HREF=\"http://web.archive.org/web/20051024212819fw_/http://www.rallymodels.co.uk:80/delta.htm\" TARGET=\"_blank\">http://web.archive.org/web/20051024212819fw_/http://www.rallymodels.co.uk:80/delta.htm</A><BR/><BR/><A HREF=\"https://www.facebook.com/pg/worldrallyarchive/photos/?tab=album&album_id=1124946130897102\" TARGET=\"_blank\">https://www.facebook.com/pg/worldrallyarchive/photos/?tab=album&amp;album_id=1124946130897102</A><BR/><BR/><A HREF=\"https://photos.app.goo.gl/4alXgpOJHaUedPwM2\" TARGET=\"_blank\">https://photos.app.goo.gl/4alXgpOJHaUedPwM2</A><BR/><BR/><A HREF=\"http://www.scale143.com/viewtopic.php?f=31&t=8649&p=361779#p361779\" TARGET=\"_blank\">http://www.scale143.com/viewtopic.php?f=31&amp;t=8649&amp;p=361779#p361779</A><BR/><BR/><BR/><b>HPI 8224 Lancia Delta Evo 1993 1,000 Lakes Rally 4th Place T. Mäkinen/S. Harjanne</b><BR/><BR/><BR/><BR/>Tommi Mäkinen and Seppo Harjanne contested 3 rounds of the 1993 WRC season for the Astra Racing team out of Italy. One of those rounds was his “home” event, the 1,000 Lakes Rally. This was the 7th time he competed in the event and it was his best finish yet. Mäkinen won three special stages and finished the rally in the same position as he started - in 4th place.<BR/><BR/><BR/><BR/> <BR/><BR/> <BR/><BR/><BR/><b>Sources</b><BR/><A HREF=\"https://www.facebook.com/pg/worldrallyarchive/photos/?tab=album&amp;album_id=1124946130897102\">World Rally Archive. 1973-1993 - Photos</A> (photo)<BR/><A HREF=\"https://en.wikipedia.org/wiki/1993_World_Rally_Championship\">1993 World Rally Championship - Wikipedia</A><BR/><A HREF=\"https://en.wikipedia.org/wiki/Tommi_Mäkinen#Career\">Tommi Mäkinen - Wikipedia</A><BR/><A HREF=\"https://www.ewrc-results.com/times/536-1000-lakes-rally-1993/\">Stage times 1000 Lakes Rally 1993</A><BR/>"}