{"images":["1"],"scale":"1:43","brand":"IXO","catalogNo":"RAC135","manufacturer":"Renault","model":"17 Gordini","year":1974,"event":"Rallye du Maroc","eventCode":"Rallye du Maroc","carNumber":6,"driver1":"J. L. Therier","driver2":"M. Vial","competitionClass":"Group 2","notes":"<A HREF=\"http://www.ixomodels.com/index.php/car/popup/1196\" TARGET=\"_blank\">http://www.ixomodels.com/index.php/car/popup/1196</A><BR/><BR/>RRR: £22.00<BR/>IXO Store: 30.00<BR/><BR/><A HREF=\"https://www.ewrc-results.com/final/14902-rallye-du-maroc-1974/\" TARGET=\"_blank\">https://www.ewrc-results.com/final/14902-rallye-du-maroc-1974/</A><BR/><BR/><A HREF=\"https://en.wikipedia.org/wiki/1974_World_Rally_Championship\" TARGET=\"_blank\">https://en.wikipedia.org/wiki/1974_World_Rally_Championship</A><BR/>"}