{"images":["1","2","3","4","5"],"scale":"1:64","brand":"CM's Corp.","catalogNo":"FIAT","manufacturer":"Fiat","model":"131 Abarth","year":1977,"event":"Rallye Sanremo","eventCode":"Rallye Sanremo","carNumber":9,"driver1":"J. C. Andruet","driver2":"C. Delferrier","competitionClass":"Group 4","notes":"<A HREF=\"http://www.cmscorp.jp/products/wrcex_fiat131_abarth.html\" TARGET=\"_blank\">http://www.cmscorp.jp/products/wrcex_fiat131_abarth.html</A><BR/><BR/><A HREF=\"https://www.ewrc-results.com/final/11623-rallye-sanremo-1977/\" TARGET=\"_blank\">https://www.ewrc-results.com/final/11623-rallye-sanremo-1977/</A><BR/><BR/><A HREF=\"https://en.wikipedia.org/wiki/1977_World_Rally_Championship\" TARGET=\"_blank\">https://en.wikipedia.org/wiki/1977_World_Rally_Championship</A><BR/>"}